composabl_train/main.cpython-311-darwin.so
composabl_train/__init__.cpython-311-darwin.so
composabl_train/config/__init__.cpython-311-darwin.so
composabl_train/config/env_config.cpython-311-darwin.so
composabl_train/config/step_info.cpython-311-darwin.so
composabl_train/env_processors/__init__.cpython-311-darwin.so
composabl_train/utils/env_validator.cpython-311-darwin.so
composabl_train/utils/validate_util.cpython-311-darwin.so
composabl_train/utils/onnx_helper.cpython-311-darwin.so
composabl_train/utils/__init__.cpython-311-darwin.so
composabl_train/env/env_composabl.cpython-311-darwin.so
composabl_train/env/env_mgr.cpython-311-darwin.so
composabl_train/env/env_composabl_multi_agent.cpython-311-darwin.so
composabl_train/env/__init__.cpython-311-darwin.so
composabl_train/v2/skill_processor_component.cpython-311-darwin.so
composabl_train/v2/controller_component.cpython-311-darwin.so
composabl_train/v2/__init__.cpython-311-darwin.so
composabl_train/model/skill_model_coordinated.cpython-311-darwin.so
composabl_train/model/__init__.cpython-311-darwin.so
composabl_train/model/skill_model.cpython-311-darwin.so
composabl_train/evaluation/evaluate.cpython-311-darwin.so
composabl_train/evaluation/__init__.cpython-311-darwin.so
composabl_train/actor/sim_mgr_actor.cpython-311-darwin.so
composabl_train/actor/metrics_actor.cpython-311-darwin.so
composabl_train/actor/__init__.cpython-311-darwin.so
composabl_train/actor/actor.cpython-311-darwin.so
composabl_train/trainer/create_skill_trainer.cpython-311-darwin.so
composabl_train/trainer/trainer.cpython-311-darwin.so
composabl_train/trainer/algorithm_config.cpython-311-darwin.so
composabl_train/trainer/training_callbacks.cpython-311-darwin.so
composabl_train/trainer/composabl_ppo.cpython-311-darwin.so
composabl_train/trainer/skill_trainer.cpython-311-darwin.so
composabl_train/trainer/skill_trainer_base.cpython-311-darwin.so
composabl_train-0.19.1.dist-info/RECORD
composabl_train-0.19.1.dist-info/WHEEL
composabl_train-0.19.1.dist-info/top_level.txt
composabl_train-0.19.1.dist-info/METADATA
