Metadata-Version: 2.4
Name: composabl-train
Version: 0.19.1
Summary: a distributed trainer to be able to train agents across a cluster of machines
Author-email: Hunter Park <hunter@composabl.com>
Requires-Python: >=3.10, <3.13
Requires-Dist: composabl-api>=0.19.1
Requires-Dist: composabl-core>=0.19.1
Requires-Dist: networkx==3.1
Requires-Dist: docker==6.1.3
Requires-Dist: kubernetes==27.2.0
Requires-Dist: pytest-asyncio
Requires-Dist: redis
Requires-Dist: ray[rllib]==2.12.0
Requires-Dist: urllib3==1.26.12
Requires-Dist: torch==2.5.1
Requires-Dist: ruff
Requires-Dist: opencv-python-headless
Requires-Dist: imageio
Requires-Dist: onnx
Requires-Dist: onnxruntime
Dynamic: description
Dynamic: description-content-type
Dynamic: requires-python
